anoncreds/__init__.py
anoncreds/bindings.py
anoncreds/error.py
anoncreds/libanoncreds.dylib
anoncreds/types.py
anoncreds/version.py
anoncreds-0.2.3.dist-info/METADATA
anoncreds-0.2.3.dist-info/WHEEL
anoncreds-0.2.3.dist-info/top_level.txt
anoncreds-0.2.3.dist-info/RECORD
