Metadata-Version: 2.1
Name: anoncreds
Version: 0.2.3
Summary: UNKNOWN
Home-page: https://github.com/hyperledger/anoncreds-rs
Author: Hyperledger Anoncreds Contributors
Author-email: anoncreds@lists.hyperledger.org
License: UNKNOWN
Platform: UNKNOWN
Classifier: Programming Language :: Python :: 3
Classifier: License :: OSI Approved :: Apache Software License
Classifier: Operating System :: OS Independent
Requires-Python: >=3.6.3
